xraysink/__init__.py
xraysink/asgi/__init__.py
xraysink/asgi/middleware.py
xraysink/config.py
xraysink/context.py
xraysink/py.typed
xraysink/tasks.py
xraysink/util.py
xraysink-1.6.2.dist-info/LICENSE
xraysink-1.6.2.dist-info/METADATA
xraysink-1.6.2.dist-info/WHEEL
xraysink-1.6.2.dist-info/RECORD
