Metadata-Version: 2.1
Name: xraysink
Version: 1.6.2
Summary: Instrument asyncio Python for distributed tracing with AWS X-Ray.
Home-page: https://github.com/garyd203/xraysink
License: Apache 2.0
Keywords: AWS,XRay,python,asyncio,distributed-tracing
Author: Gary Donovan
Author-email: gazza@gazza.id.au
Requires-Python: >=3.7.9,<4.0.0
Classifier: Development Status :: 5 - Production/Stable
Classifier: Environment :: Web Environment
Classifier: Framework :: AsyncIO
Classifier: Intended Audience :: Developers
Classifier: License :: OSI Approved :: Apache Software License
Classifier: License :: Other/Proprietary License
Classifier: Natural Language :: English
Classifier: Operating System :: OS Independent
Classifier: Programming Language :: Python
Classifier: Programming Language :: Python :: 3
Classifier: Programming Language :: Python :: 3.8
Classifier: Programming Language :: Python :: 3.9
Classifier: Programming Language :: Python :: 3.10
Classifier: Programming Language :: Python :: 3.11
Classifier: Programming Language :: Python :: 3 :: Only
Classifier: Programming Language :: Python :: 3.7
Classifier: Topic :: Software Development :: Libraries :: Application Frameworks
Classifier: Topic :: System :: Monitoring
Requires-Dist: aws_xray_sdk (>=2,<3)
Requires-Dist: wrapt (>=1.15,<2.0)
Project-URL: Documentation, https://github.com/garyd203/xraysink
Project-URL: Repository, https://github.com/garyd203/xraysink
